basic_shit/__init__.py
basic_shit-1.0.0.dist-info/licenses/LICENSE
basic_shit-1.0.0.dist-info/METADATA
basic_shit-1.0.0.dist-info/WHEEL
basic_shit-1.0.0.dist-info/top_level.txt
basic_shit-1.0.0.dist-info/RECORD
