Metadata-Version: 2.4
Name: basic-shit
Version: 1.0.0
Summary: Finding your project root in Python. You know, basic shit.
Author-email: Your Name <kdezer1992@gmail.com>
License: MIT
Project-URL: Homepage, https://github.com/kevx-dev
Project-URL: Repository, https://github.com/kevx-dev/basic-shit
Keywords: project,root,path,directory,finder
Classifier: Development Status :: 4 - Beta
Classifier: Intended Audience :: Developers
Classifier: License :: OSI Approved :: MIT License
Classifier: Programming Language :: Python :: 3
Classifier: Programming Language :: Python :: 3.8
Classifier: Programming Language :: Python :: 3.9
Classifier: Programming Language :: Python :: 3.10
Classifier: Programming Language :: Python :: 3.11
Classifier: Programming Language :: Python :: 3.12
Classifier: Topic :: Software Development :: Libraries :: Python Modules
Requires-Python: >=3.8
License-File: LICENSE
Provides-Extra: dev
Requires-Dist: pytest>=7.0.0; extra == "dev"
Requires-Dist: pytest-cov>=4.0.0; extra == "dev"
Dynamic: license-file
